[
  {
    "ka": "",
    "hi": "おいしい",
    "en": "delicious"
  },
  {
    "ka": "多い",
    "hi": "おおい",
    "en": "many"
  },
  {
    "ka": "大きい",
    "hi": "おおきい",
    "en": "big"
  },
  {
    "ka": "大きな",
    "hi": "おおきな",
    "en": "big"
  },
  {
    "ka": "大勢",
    "hi": "おおぜい",
    "en": "great number of people"
  },
  {
    "ka": "お母さん",
    "hi": "おかあさん",
    "en": "(honorable) mother"
  },
  {
    "ka": "お菓子",
    "hi": "おかし",
    "en": "sweets, candy"
  },
  {
    "ka": "お金",
    "hi": "おかね",
    "en": "money"
  },
  {
    "ka": "起きる",
    "hi": "おきる",
    "en": "to get up"
  },
  {
    "ka": "置く",
    "hi": "おく",
    "en": "to put"
  },
  {
    "ka": "奥さん",
    "hi": "おくさん",
    "en": "(honorable) wife"
  },
  {
    "ka": "お酒",
    "hi": "おさけ",
    "en": "alcohol, rice wine"
  },
  {
    "ka": "お皿",
    "hi": "おさら",
    "en": "plate, dish"
  },
  {
    "ka": "伯父/叔父",
    "hi": "おじいさん",
    "en": "grandfather, male senior citizen"
  },
  {
    "ka": "教える",
    "hi": "おしえる",
    "en": "to teach, to tell"
  },
  {
    "ka": "伯父/叔父",
    "hi": "おじさん",
    "en": "uncle, middle aged gentleman"
  },
  {
    "ka": "押す",
    "hi": "おす",
    "en": "to push, to stamp something"
  },
  {
    "ka": "遅い",
    "hi": "おそい",
    "en": "late, slow"
  },
  {
    "ka": "お茶",
    "hi": "おちゃ",
    "en": "green tea"
  },
  {
    "ka": "お手洗い",
    "hi": "おてあらい",
    "en": "bathroom"
  },
  {
    "ka": "お父さん",
    "hi": "おとうさん",
    "en": "(honorable) father"
  },
  {
    "ka": "弟",
    "hi": "おとうと",
    "en": "younger brother"
  },
  {
    "ka": "男",
    "hi": "おとこ",
    "en": "Man"
  },
  {
    "ka": "男の子",
    "hi": "おとこのこ",
    "en": "Boy"
  },
  {
    "ka": "一昨日",
    "hi": "おととい",
    "en": "day before yesterday"
  },
  {
    "ka": "一昨年",
    "hi": "おととし",
    "en": "year before last"
  },
  {
    "ka": "大人",
    "hi": "おとな",
    "en": "Adult"
  },
  {
    "ka": "",
    "hi": "おなか",
    "en": "stomach"
  },
  {
    "ka": "同じ",
    "hi": "おなじ",
    "en": "same"
  },
  {
    "ka": "お兄さん",
    "hi": "おにいさん",
    "en": "(honorable) older brother"
  },
  {
    "ka": "お姉さん",
    "hi": "おねえさん",
    "en": "(honorable) older sister"
  },
  {
    "ka": "",
    "hi": "おばあさん",
    "en": "grandmother, female senior-citizen"
  },
  {
    "ka": "伯母さん/叔母さん",
    "hi": "おばさん",
    "en": "Aunt"
  },
  {
    "ka": "お風呂",
    "hi": "おふろ",
    "en": "Bath"
  },
  {
    "ka": "お弁当",
    "hi": "おべんとう",
    "en": "boxed lunch"
  },
  {
    "ka": "覚える",
    "hi": "おぼえる",
    "en": "to remember"
  },
  {
    "ka": "",
    "hi": "おまわりさん",
    "en": "friendly term for policeman"
  },
  {
    "ka": "重い",
    "hi": "おもい",
    "en": "Heavy"
  },
  {
    "ka": "",
    "hi": "おもしろい",
    "en": "Interesting"
  },
  {
    "ka": "泳ぐ",
    "hi": "およぐ",
    "en": "to swim"
  },
  {
    "ka": "降りる",
    "hi": "おりる",
    "en": "to get off, to descend"
  },
  {
    "ka": "終る",
    "hi": "おわる",
    "en": "to finish"
  },
  {
    "ka": "音楽",
    "hi": "おんがく",
    "en": "Music"
  },
  {
    "ka": "女",
    "hi": "おんな",
    "en": "Woman"
  },
  {
    "ka": "女の子",
    "hi": "おんなのこ",
    "en": "Girl"
  }
]